imessage_max/__init__.py
imessage_max/contacts.py
imessage_max/db.py
imessage_max/models.py
imessage_max/parsing.py
imessage_max/phone.py
imessage_max/queries.py
imessage_max/server.py
imessage_max/suggestions.py
imessage_max/time_utils.py
imessage_max/version_check.py
imessage_max/enrichment/__init__.py
imessage_max/enrichment/audio.py
imessage_max/enrichment/images.py
imessage_max/enrichment/links.py
imessage_max/enrichment/videos.py
imessage_max/tools/__init__.py
imessage_max/tools/find_chat.py
imessage_max/tools/get_active.py
imessage_max/tools/get_attachment.py
imessage_max/tools/get_context.py
imessage_max/tools/get_messages.py
imessage_max/tools/get_unread.py
imessage_max/tools/list_attachments.py
imessage_max/tools/list_chats.py
imessage_max/tools/search.py
imessage_max/tools/send.py
imessage_max-0.4.4.dist-info/METADATA
imessage_max-0.4.4.dist-info/WHEEL
imessage_max-0.4.4.dist-info/entry_points.txt
imessage_max-0.4.4.dist-info/licenses/LICENSE
imessage_max-0.4.4.dist-info/RECORD
