Metadata-Version: 2.4
Name: imessage-max
Version: 0.4.4
Summary: Intent-aligned MCP server for iMessage
Author: Rob Dezendorf
License-Expression: MIT
License-File: LICENSE
Requires-Python: >=3.10
Requires-Dist: beautifulsoup4>=4.12
Requires-Dist: fastmcp<3,>=0.4
Requires-Dist: httpx>=0.27
Requires-Dist: imageio-ffmpeg>=0.5
Requires-Dist: phonenumbers>=8.13
Requires-Dist: pillow-heif>=0.16
Requires-Dist: pillow>=10.0
Requires-Dist: pyobjc-framework-contacts>=12.1
Requires-Dist: python-dateutil>=2.8
Provides-Extra: dev
Requires-Dist: pytest-asyncio>=0.21; extra == 'dev'
Requires-Dist: pytest-httpx>=0.30; extra == 'dev'
Requires-Dist: pytest>=7.0; extra == 'dev'
